[
    {
        "name": "Project One",
        "description": "This is a description for Project One.",
        "technologies": ["JavaScript", "React", "Node.js"],
        "link": "https://example.com/project-one",
        "image": "https://via.placeholder.com/150"
    },
    {
        "name": "Project Two",
        "description": "This is a description for Project Two.",
        "technologies": ["Python", "Django", "PostgreSQL"],
        "link": "https://example.com/project-two",
        "image": "https://via.placeholder.com/150"
    },
    {
        "name": "Project Three",
        "description": "This is a description for Project Three.",
        "technologies": ["Java", "Spring Boot", "MySQL"],
        "link": "https://example.com/project-three",
        "image": "https://via.placeholder.com/150"
    }
]